Workbook

Sheet Financials>>

Sheet Offline retail
A1: Offline retail stores
A2: All figures in ₹ crore
A4: x | B4: Profit and loss
B5: Particulars | C5: FY24 | D5: FY25 | E5: FY26 | F5: FY27 | G5: FY28 | H5: FY29 | I5: FY30
B6: Bags revenue | C6: 7.7 | D6: 20 | E6: 40 | F6: =E6*(1+Assumptions!C6) | G6: =F6*(1+Assumptions!D6) | H6: =G6*(1+Assumptions!E6) | I6: =H6*(1+Assumptions!F6)
B7: Accessories revenue | C7: 1.6 | D7: 4.5 | E7: 10 | F7: =E7*(1+Assumptions!C7) | G7: =F7*(1+Assumptions!D7) | H7: =G7*(1+Assumptions!E7) | I7: =H7*(1+Assumptions!F7)
B8: Total revenue | C8: =C6+C7 | D8: =D6+D7 | E8: =E6+E7 | F8: =F6+F7 | G8: =G6+G7 | H8: =H6+H7 | I8: =I6+I7
B9: Cost of goods sold | C9: 4.9 | D9: 12.3 | E9: 24 | F9: =F8*(1-Assumptions!C8) | G9: =G8*(1-Assumptions!D8) | H9: =H8*(1-Assumptions!E8) | I9: =I8*(1-Assumptions!F8)
B10: Gross margin | C10: =C8-C9 | D10: =D8-D9 | E10: =E8-E9 | F10: =F8-F9 | G10: =G8-G9 | H10: =H8-H9 | I10: =I8-I9
B11: Packaging | C11: 0.1 | D11: 0.3 | E11: 0.5 | F11: =F$8*Assumptions!C9 | G11: =G$8*Assumptions!D9 | H11: =H$8*Assumptions!E9 | I11: =I$8*Assumptions!F9
B12: Payment gateway charges | C12: 0.1 | D12: 0.2 | E12: 0.4 | F12: =F$8*Assumptions!C10 | G12: =G$8*Assumptions!D10 | H12: =H$8*Assumptions!E10 | I12: =I$8*Assumptions!F10
B13: Contribution Margin-1 | C13: =C10-C11-C12 | D13: =D10-D11-D12 | E13: =E10-E11-E12 | F13: =F10-F11-F12 | G13: =G10-G11-G12 | H13: =H10-H11-H12 | I13: =I10-I11-I12
B14: Performance Marketing | C14: 0.8 | D14: 1.8 | E14: 3 | F14: =F$8*Assumptions!C11 | G14: =G$8*Assumptions!D11 | H14: =H$8*Assumptions!E11 | I14: =I$8*Assumptions!F11
B15: Contribution Margin-2 | C15: =C13-C14 | D15: =D13-D14 | E15: =E13-E14 | F15: =F13-F14 | G15: =G13-G14 | H15: =H13-H14 | I15: =I13-I14
B16: Store rent | C16: 2.2 | D16: 4.4 | E16: 7 | F16: =E16*(1+Assumptions!C12) | G16: =F16*(1+Assumptions!D12) | H16: =G16*(1+Assumptions!E12) | I16: =H16*(1+Assumptions!F12)
B17: Store staff | C17: 1.3 | D17: 2.9 | E17: 5 | F17: =E17*(1+Assumptions!C13) | G17: =F17*(1+Assumptions!D13) | H17: =G17*(1+Assumptions!E13) | I17: =H17*(1+Assumptions!F13)
B18: Offline contribution | C18: =C15-C16-C17 | D18: =D15-D16-D17 | E18: =E15-E16-E17 | F18: =F15-F16-F17 | G18: =G15-G16-G17 | H18: =H15-H16-H17 | I18: =I15-I16-I17

Sheet D2C
A1: D2C & App
A2: All figures in ₹ crore
A4: x | B4: Profit and loss
B5: Particulars | C5: FY24 | D5: FY25 | E5: FY26 | F5: FY27 | G5: FY28 | H5: FY29 | I5: FY30
B6: Bags revenue | C6: 9.6 | D6: 25 | E6: 50 | F6: =E6*(1+Assumptions!C17) | G6: =F6*(1+Assumptions!D17) | H6: =G6*(1+Assumptions!E17) | I6: =H6*(1+Assumptions!F17)
B7: Accessories revenue | C7: 3.1 | D7: 9.1 | E7: 20 | F7: =E7*(1+Assumptions!C18) | G7: =F7*(1+Assumptions!D18) | H7: =G7*(1+Assumptions!E18) | I7: =H7*(1+Assumptions!F18)
B8: Total revenue | C8: =C6+C7 | D8: =D6+D7 | E8: =E6+E7 | F8: =F6+F7 | G8: =G6+G7 | H8: =H6+H7 | I8: =I6+I7
B9: Cost of goods sold | C9: 6.4 | D9: 16 | E9: 31.5 | F9: =F8*(1-Assumptions!C19) | G9: =G8*(1-Assumptions!D19) | H9: =H8*(1-Assumptions!E19) | I9: =I8*(1-Assumptions!F19)
B10: Gross margin | C10: =C8-C9 | D10: =D8-D9 | E10: =E8-E9 | F10: =F8-F9 | G10: =G8-G9 | H10: =H8-H9 | I10: =I8-I9
B11: Packaging | C11: 0.2 | D11: 0.6 | E11: 1.1 | F11: =F$8*Assumptions!C20 | G11: =G$8*Assumptions!D20 | H11: =H$8*Assumptions!E20 | I11: =I$8*Assumptions!F20
B12: Payment gateway charges | C12: 0.2 | D12: 0.6 | E12: 1.1 | F12: =F$8*Assumptions!C21 | G12: =G$8*Assumptions!D21 | H12: =H$8*Assumptions!E21 | I12: =I$8*Assumptions!F21
B13: Shipping | C13: 0.5 | D13: 1.2 | E13: 2.1 | F13: =F$8*Assumptions!C22 | G13: =G$8*Assumptions!D22 | H13: =H$8*Assumptions!E22 | I13: =I$8*Assumptions!F22
B14: Contribution Margin-1 | C14: =C10-C11-C12-C13 | D14: =D10-D11-D12-D13 | E14: =E10-E11-E12-E13 | F14: =F10-F11-F12-F13 | G14: =G10-G11-G12-G13 | H14: =H10-H11-H12-H13 | I14: =I10-I11-I12-I13
B15: Performance marketing | C15: 5.2 | D15: 11.7 | E15: 19.6 | F15: =F$8*Assumptions!C23 | G15: =G$8*Assumptions!D23 | H15: =H$8*Assumptions!E23 | I15: =I$8*Assumptions!F23
B16: D2C contribution | C16: =C14-C15 | D16: =D14-D15 | E16: =E14-E15 | F16: =F14-F15 | G16: =G14-G15 | H16: =H14-H15 | I16: =I14-I15

Sheet Consolidated 
A1: Consolidated financials
A2: All figures in ₹ crore
A4: x | B4: Consolidated financials
B5: Particulars | C5: FY24 | D5: FY25 | E5: FY26 | F5: FY27 | G5: FY28 | H5: FY29 | I5: FY30
B6: Offline revenue | C6: ='Offline retail'!C8 | D6: ='Offline retail'!D8 | E6: ='Offline retail'!E8 | F6: ='Offline retail'!F8 | G6: ='Offline retail'!G8 | H6: ='Offline retail'!H8 | I6: ='Offline retail'!I8
B7: D2C revenue | C7: =D2C!C8 | D7: =D2C!D8 | E7: =D2C!E8 | F7: =D2C!F8 | G7: =D2C!G8 | H7: =D2C!H8 | I7: =D2C!I8
B8: Total revenue | C8: =C6+C7 | D8: =D6+D7 | E8: =E6+E7 | F8: =F6+F7 | G8: =G6+G7 | H8: =H6+H7 | I8: =I6+I7
B9: Offline contribution | C9: ='Offline retail'!C18 | D9: ='Offline retail'!D18 | E9: ='Offline retail'!E18 | F9: ='Offline retail'!F18 | G9: ='Offline retail'!G18 | H9: ='Offline retail'!H18 | I9: ='Offline retail'!I18
B10: D2C contribution | C10: =D2C!C16 | D10: =D2C!D16 | E10: =D2C!E16 | F10: =D2C!F16 | G10: =D2C!G16 | H10: =D2C!H16 | I10: =D2C!I16
B11: Total contribution | C11: =C9+C10 | D11: =D9+D10 | E11: =E9+E10 | F11: =F9+F10 | G11: =G9+G10 | H11: =H9+H10 | I11: =I9+I10
B12: Head office salaries | C12: 2.2 | D12: 3.3 | E12: 5 | F12: =E12*(1+Assumptions!C27) | G12: =F12*(1+Assumptions!D27) | H12: =G12*(1+Assumptions!E27) | I12: =H12*(1+Assumptions!F27)
B13: Brand marketing | C13: 1.2 | D13: 1.9 | E13: 3 | F13: =E13*(1+Assumptions!C28) | G13: =F13*(1+Assumptions!D28) | H13: =G13*(1+Assumptions!E28) | I13: =H13*(1+Assumptions!F28)
B14: Technology and platform | C14: 0.4 | D14: 0.7 | E14: 1.2 | F14: =E14*(1+Assumptions!C29) | G14: =F14*(1+Assumptions!D29) | H14: =G14*(1+Assumptions!E29) | I14: =H14*(1+Assumptions!F29)
B15: Other general and administrative | C15: 0.3 | D15: 0.6 | E15: 1 | F15: =E15*(1+Assumptions!C30) | G15: =F15*(1+Assumptions!D30) | H15: =G15*(1+Assumptions!E30) | I15: =H15*(1+Assumptions!F30)
B16: EBITDA | C16: =C11-C12-C13-C14-C15 | D16: =D11-D12-D13-D14-D15 | E16: =E11-E12-E13-E14-E15 | F16: =F11-SUM(F12:F15) | G16: =G11-SUM(G12:G15) | H16: =H11-SUM(H12:H15) | I16: =I11-SUM(I12:I15)
B17: Depreciation | C17: 0.4 | D17: 1.3 | E17: 2.5 | F17: =Assumptions!$C$34 | G17: =Assumptions!$C$34 | H17: =Assumptions!$C$34+Assumptions!$C$38 | I17: =Assumptions!$C$34+Assumptions!$C$38
B18: EBIT | C18: =C16-C17 | D18: =D16-D17 | E18: =E16-E17 | F18: =F16-F17 | G18: =G16-G17 | H18: =H16-H17 | I18: =I16-I17
B19: Interest | C19: 0 | D19: 0 | E19: 0 | F19: =Assumptions!$C$42*Assumptions!$C$43 | G19: =Assumptions!$C$42*Assumptions!$C$43 | H19: =Assumptions!$C$42*Assumptions!$C$43 | I19: =Assumptions!$C$42*Assumptions!$C$43
B20: Profit before tax | C20: =C18-C19 | D20: =D18-D19 | E20: =E18-E19 | F20: =F18-F19 | G20: =G18-G19 | H20: =H18-H19 | I20: =I18-I19
B21: Tax | C21: =MAX(0,C20*Assumptions!$C$41) | D21: =MAX(0,D20*Assumptions!$C$41) | E21: =MAX(0,E20*Assumptions!$C$41) | F21: =MAX(0,F20*Assumptions!$C$41) | G21: =MAX(0,G20*Assumptions!$C$41) | H21: =MAX(0,H20*Assumptions!$C$41) | I21: =MAX(0,I20*Assumptions!$C$41)
B22: Profit after tax | C22: =C20-C21 | D22: =D20-D21 | E22: =E20-E21 | F22: =F20-F21 | G22: =G20-G21 | H22: =H20-H21 | I22: =I20-I21

Sheet Valuation>>

Sheet DCF (FCFE)
A1: Discounted Cash Flow Valuation (FCFE)
A2: All figures in ₹ crore
A4: x | B4: Discounting factor | C4: 0.21
A5: x | B5: Terminal growth rate | C5: 0.05
A7: x | B7: Calculating value of TrekLite using DCF
B8: Particulars | C8: FY27 | D8: FY28 | E8: FY29 | F8: FY30
B9: Profit after tax | C9: ='Consolidated '!F22 | D9: ='Consolidated '!G22 | E9: ='Consolidated '!H22 | F9: ='Consolidated '!I22
B10: Add: non-cash expenses | C10: ='Consolidated '!F17 | D10: ='Consolidated '!G17 | E10: ='Consolidated '!H17 | F10: ='Consolidated '!I17
B11: Cash profit (for equity holders) | C11: =C9+C10 | D11: =D9+D10 | E11: =E9+E10 | F11: =F9+F10
B12: Less: Additional working capital required | C12: =D45 | D12: =E45 | E12: =F45 | F12: =G45
B13: Less: Capex for bag-stitching machines | C13: 0 | D13: 0 | E13: 5 | F13: 0
B14: Free cash flows for equity (FCFE) | C14: =C11-C12-C13 | D14: =D11-D12-D13 | E14: =E11-E12-E13 | F14: =F11-F12-F13
B15: Terminal value | F15: =F14*(1+C5)/(C4-C5)
A17: x | B17: Years to discount | C17: 1 | D17: 2 | E17: 3 | F17: 4
B18: Discounting factor | C18: =1/(1+$C$4)^C17 | D18: =1/(1+$C$4)^D17 | E18: =1/(1+$C$4)^E17 | F18: =1/(1+$C$4)^F17
A20: x | B20: Present value of free cash flows | C20: =C14*C18 | D20: =D14*D18 | E20: =E14*E18 | F20: =F14*F18
B21: Present value of terminal value | F21: =F15*F18
A23: x | B23: Equity value as per DCF | C23: =C20+D20+E20+F20+F21
A25: x | B25: Calculating Net Present Value (NPV)
B26: Particulars | C26: 46112
B27: Investor's preferred value | C27: =C23
B28: Founder's preferred value | C28: 170
B29: Net present Value (NPV) | C29: =C27-C28
A31: x | B31: Calculating Internal Rate of Return (IRR)
B32: Particulars | C32: 46112 | D32: 46477 | E32: 46843 | F32: 47208 | G32: 47573
B33: Cash flows | C33: =-C28 | D33: =C14+C15 | E33: =D14+D15 | F33: =E14+E15 | G33: =F14+F15
B34: Internal Rate of Return (IRR) | C34: =IRR(C33:G33)
A36: x | B36: Scenarios
B37: Case | C37: Multiple of base | D37: Valuation
B38: Upside | C38: 1.2 | D38: =D39*C38
B39: Base | C39: 1 | D39: =C23
B40: Downside | C40: 0.8 | D40: =D39*C40
A42: x | B42: Working for working capital
B43: Particulars | C43: FY26 | D43: FY27 | E43: FY28 | F43: FY29 | G43: FY30
B44: Working capital | C44: =Assumptions!C40 | D44: =Assumptions!$C$39*'Consolidated '!F8 | E44: =Assumptions!$C$39*'Consolidated '!G8 | F44: =Assumptions!$C$39*'Consolidated '!H8 | G44: =Assumptions!$C$39*'Consolidated '!I8
B45: Increase | D45: =D44-C44 | E45: =E44-D44 | F45: =F44-E44 | G45: =G44-F44

Sheet Relative Valuation
A1: Relative Valuation

Sheet Sum of parts
A1: Sum of parts valuation

Sheet First Chicago
A1: First Chicago Method

Sheet Exit Pegged Valuation
A1: First Chicago Method

Sheet Football Field
A1: Football field

Sheet Assumptions
A1: Assumptions Sheet
A4: x | B4: Offline retail
B5: Particulars | C5: FY27 | D5: FY28 | E5: FY29 | F5: FY30
B6: Bags revenue growth (YoY) | C6: 0.4 | D6: 0.3 | E6: 0.25 | F6: 0.2
B7: Accessories revenue growth (YoY) | C7: 0.5 | D7: 0.4 | E7: 0.3 | F7: 0.25
B8: Gross margin (% of revenue) | C8: 0.52 | D8: 0.52 | E8: 0.52 | F8: 0.52
B9: Packaging (% of revenue) | C9: 0.01 | D9: 0.01 | E9: 0.01 | F9: 0.01
B10: Payment gateway (% of revenue) | C10: 0.008 | D10: 0.008 | E10: 0.008 | F10: 0.008
B11: Performance marketing (% of revenue) | C11: 0.06 | D11: 0.06 | E11: 0.06 | F11: 0.06
B12: Store rent (YoY) | C12: 0.3 | D12: 0.25 | E12: 0.2 | F12: 0.15
B13: Store staff (YoY) | C13: 0.3 | D13: 0.25 | E13: 0.2 | F13: 0.15
A15: x | B15: D2C
B16: Particulars | C16: FY27 | D16: FY28 | E16: FY29 | F16: FY30
B17: Bags revenue growth (YoY) | C17: 0.35 | D17: 0.3 | E17: 0.25 | F17: 0.2
B18: Accessories revenue growth (YoY) | C18: 0.45 | D18: 0.35 | E18: 0.3 | F18: 0.25
B19: Gross margin (% of revenue) | C19: 0.55 | D19: 0.55 | E19: 0.55 | F19: 0.55
B20: Packaging (% of revenue) | C20: 0.015 | D20: 0.015 | E20: 0.015 | F20: 0.015
B21: Payment gateway (% of revenue) | C21: 0.015 | D21: 0.015 | E21: 0.015 | F21: 0.015
B22: Shipping (% of revenue) | C22: 0.03 | D22: 0.03 | E22: 0.03 | F22: 0.03
B23: Performance marketing (% of revenue) | C23: 0.28 | D23: 0.27 | E23: 0.26 | F23: 0.25
A25: x | B25: Common cost growth (YoY)
B26: Particulars | C26: FY27 | D26: FY28 | E26: FY29 | F26: FY30
B27: Head office salaries | C27: 0.3 | D27: 0.25 | E27: 0.2 | F27: 0.15
B28: Brand marketing | C28: 0.35 | D28: 0.3 | E28: 0.25 | F28: 0.2
B29: Technology and platform | C29: 0.25 | D29: 0.2 | E29: 0.18 | F29: 0.15
B30: Other general and administrative | C30: 0.2 | D30: 0.18 | E30: 0.15 | F30: 0.12
A32: x | B32: Corporate
B33: Particulars | C33: Value
B34: Depreciation on existing fit-outs p.a. (₹ cr) (FY26 onwards) | C34: 2.5
B35: Bag-stitching machines, total cost (₹ cr) | C35: 5
B36: Year of purchase | C36: FY29
B37: Machine life (years) | C37: 5
B38: Additional depreciation (FY29 onwards) | C38: =C35/C37
B39: Working capital (% of revenue) | C39: 0.15
B40: Working capital at 31 Mar 2026 (₹ cr) | C40: 18
B41: Tax rate | C41: 0.25
B42: Debt as on 31/3/2026 (₹ cr) | C42: 30
B43: Interest cost (%) | C43: 0.12
