Workbook

Sheet Financials>>

Sheet Offline retail
A1: Offline retail stores
A2: All figures in ₹ crore
A4: x | B4: Profit and loss
B5: Particulars | C5: FY24 | D5: FY25 | E5: FY26 | F5: FY27 | G5: FY28 | H5: FY29 | I5: FY30
B6: Bags revenue | C6: 11.5 | D6: 30 | E6: 60
B7: Accessories revenue | C7: 2.4 | D7: 6.8 | E7: 15
B8: Total revenue | C8: =C6+C7 | D8: =D6+D7 | E8: =E6+E7
B9: Cost of goods sold | C9: 7.9 | D9: 19.9 | E9: 39
B10: Gross margin | C10: =C8-C9 | D10: =D8-D9 | E10: =E8-E9
B11: Packaging | C11: 0.2 | D11: 0.5 | E11: 0.9
B12: Payment gateway charges | C12: 0.2 | D12: 0.4 | E12: 0.8
B13: Contribution Margin-1 | C13: =C10-C11-C12 | D13: =D10-D11-D12 | E13: =E10-E11-E12
B14: Performance Marketing | C14: 0.9 | D14: 2 | E14: 3.4
B15: Contribution Margin-2 | C15: =C13-C14 | D15: =D13-D14 | E15: =E13-E14
B16: Store rent | C16: 3.4 | D16: 6.9 | E16: 11
B17: Store staff | C17: 2.1 | D17: 4.7 | E17: 8
B18: Offline contribution | C18: =C15-C16-C17 | D18: =D15-D16-D17 | E18: =E15-E16-E17

Sheet D2C
A1: D2C & App
A2: All figures in ₹ crore
A4: x | B4: Profit and loss
B5: Particulars | C5: FY24 | D5: FY25 | E5: FY26 | F5: FY27 | G5: FY28 | H5: FY29 | I5: FY30
B6: Bags revenue | C6: 8.7 | D6: 22.5 | E6: 45
B7: Accessories revenue | C7: 3.9 | D7: 11.4 | E7: 25
B8: Total revenue | C8: =C6+C7 | D8: =D6+D7 | E8: =E6+E7
B9: Cost of goods sold | C9: 6.4 | D9: 16.3 | E9: 32.2
B10: Gross margin | C10: =C8-C9 | D10: =D8-D9 | E10: =E8-E9
B11: Packaging | C11: 0.2 | D11: 0.6 | E11: 1.1
B12: Payment gateway charges | C12: 0.2 | D12: 0.5 | E12: 0.8
B13: Shipping | C13: 0.5 | D13: 1.1 | E13: 2
B14: Contribution Margin-1 | C14: =C10-C11-C12-C13 | D14: =D10-D11-D12-D13 | E14: =E10-E11-E12-E13
B15: Performance marketing | C15: 4.9 | D15: 11.2 | E15: 18.9
B16: D2C contribution | C16: =C14-C15 | D16: =D14-D15 | E16: =E14-E15

Sheet Consolidated 
A1: Consolidated financials
A2: All figures in ₹ crore
A4: x | B4: Consolidated financials
B5: Particulars | C5: FY24 | D5: FY25 | E5: FY26 | F5: FY27 | G5: FY28 | H5: FY29 | I5: FY30
B6: Offline revenue | C6: ='Offline retail'!C8 | D6: ='Offline retail'!D8 | E6: ='Offline retail'!E8
B7: D2C revenue | C7: =D2C!C8 | D7: =D2C!D8 | E7: =D2C!E8
B8: Total revenue | C8: =C6+C7 | D8: =D6+D7 | E8: =E6+E7
B9: Offline contribution | C9: ='Offline retail'!C18 | D9: ='Offline retail'!D18 | E9: ='Offline retail'!E18
B10: D2C contribution | C10: =D2C!C16 | D10: =D2C!D16 | E10: =D2C!E16
B11: Total contribution | C11: =C9+C10 | D11: =D9+D10 | E11: =E9+E10
B12: Head office salaries | C12: 3.1 | D12: 4.7 | E12: 7
B13: Brand marketing | C13: 1.6 | D13: 2.6 | E13: 4
B14: Technology and platform | C14: 0.7 | D14: 1.2 | E14: 2
B15: Other general and administrative | C15: 0.5 | D15: 1 | E15: 1.6
B16: EBITDA | C16: =C11-C12-C13-C14-C15 | D16: =D11-D12-D13-D14-D15 | E16: =E11-E12-E13-E14-E15
B17: Depreciation | C17: 0.6 | D17: 1.8 | E17: 3.5
B18: EBIT | C18: =C16-C17 | D18: =D16-D17 | E18: =E16-E17
B19: Interest | C19: 0 | D19: 0 | E19: 0
B20: Profit before tax | C20: =C18-C19 | D20: =D18-D19 | E20: =E18-E19
B21: Tax | C21: =MAX(0,C20*Assumptions!$C$41) | D21: =MAX(0,D20*Assumptions!$C$41) | E21: =MAX(0,E20*Assumptions!$C$41)
B22: Profit after tax | C22: =C20-C21 | D22: =D20-D21 | E22: =E20-E21

Sheet Valuation>>

Sheet DCF (FCFE)
A1: Discounted Cash Flow Valuation (FCFE)
A2: All figures in ₹ crore
A4: x | B4: Discounting factor
A5: x | B5: Terminal growth rate
A7: x | B7: Calculating value of Wanderly using DCF
B8: Particulars | C8: FY27 | D8: FY28 | E8: FY29 | F8: FY30
B9: Profit after tax
B10: Add: non-cash expenses
B11: Cash profit (for equity holders)
B12: Less: Additional working capital required
B13: Less: Capex for warehouse racking and packing line
B14: Free cash flows for equity (FCFE)
B15: Terminal value
A17: x | B17: Years to discount
B18: Discounting factor
A20: x | B20: Present value of free cash flows
B21: Present value of terminal value
A23: x | B23: Equity value as per DCF
A25: x | B25: Calculating Net Present Value (NPV)
B26: Particulars | C26: 46112
B27: Investor's preferred value
B28: Founder's preferred value
B29: Net present Value (NPV)
A31: x | B31: Calculating Internal Rate of Return (IRR)
B32: Particulars | C32: 46112 | D32: 46477 | E32: 46843 | F32: 47208 | G32: 47573
B33: Cash flows
B34: Internal Rate of Return (IRR)
A36: x | B36: Scenarios
B37: Case | C37: Multiple of base | D37: Valuation
B38: Upside
B39: Base
B40: Downside
A42: x | B42: Working for working capital
B43: Particulars | C43: FY26 | D43: FY27 | E43: FY28 | F43: FY29 | G43: FY30
B44: Working capital
B45: Increase

Sheet Relative Valuation
A1: Relative Valuation

Sheet Sum of parts
A1: Sum of parts valuation

Sheet First Chicago
A1: First Chicago Method

Sheet Exit Pegged Valuation
A1: First Chicago Method

Sheet Football Field
A1: Football field

Sheet Assumptions
A1: Assumptions Sheet
A4: x | B4: Offline retail
B5: Particulars | C5: FY27 | D5: FY28 | E5: FY29 | F5: FY30
B6: Bags revenue growth (YoY) | C6: 0.38 | D6: 0.3 | E6: 0.24 | F6: 0.18
B7: Accessories revenue growth (YoY) | C7: 0.48 | D7: 0.38 | E7: 0.3 | F7: 0.24
B8: Gross margin (% of revenue) | C8: 0.48 | D8: 0.49 | E8: 0.5 | F8: 0.5
B9: Packaging (% of revenue) | C9: 0.012 | D9: 0.012 | E9: 0.012 | F9: 0.012
B10: Payment gateway (% of revenue) | C10: 0.01 | D10: 0.01 | E10: 0.01 | F10: 0.01
B11: Performance marketing (% of revenue) | C11: 0.045 | D11: 0.045 | E11: 0.045 | F11: 0.045
B12: Store rent (YoY) | C12: 0.28 | D12: 0.22 | E12: 0.18 | F12: 0.14
B13: Store staff (YoY) | C13: 0.3 | D13: 0.24 | E13: 0.2 | F13: 0.16
A15: x | B15: D2C
B16: Particulars | C16: FY27 | D16: FY28 | E16: FY29 | F16: FY30
B17: Bags revenue growth (YoY) | C17: 0.42 | D17: 0.34 | E17: 0.26 | F17: 0.2
B18: Accessories revenue growth (YoY) | C18: 0.52 | D18: 0.4 | E18: 0.3 | F18: 0.24
B19: Gross margin (% of revenue) | C19: 0.54 | D19: 0.54 | E19: 0.54 | F19: 0.54
B20: Packaging (% of revenue) | C20: 0.015 | D20: 0.015 | E20: 0.015 | F20: 0.015
B21: Payment gateway (% of revenue) | C21: 0.012 | D21: 0.012 | E21: 0.012 | F21: 0.012
B22: Shipping (% of revenue) | C22: 0.028 | D22: 0.028 | E22: 0.028 | F22: 0.028
B23: Performance marketing (% of revenue) | C23: 0.27 | D23: 0.26 | E23: 0.25 | F23: 0.24
A25: x | B25: Common cost growth (YoY)
B26: Particulars | C26: FY27 | D26: FY28 | E26: FY29 | F26: FY30
B27: Head office salaries | C27: 0.28 | D27: 0.24 | E27: 0.2 | F27: 0.16
B28: Brand marketing | C28: 0.38 | D28: 0.32 | E28: 0.26 | F28: 0.22
B29: Technology and platform | C29: 0.28 | D29: 0.22 | E29: 0.18 | F29: 0.14
B30: Other general and administrative | C30: 0.22 | D30: 0.2 | E30: 0.16 | F30: 0.14
A32: x | B32: Corporate
B33: Particulars | C33: Value
B34: Depreciation on existing fit-outs p.a. (₹ cr) (FY26 onwards) | C34: 3.5
B35: Warehouse racking and packing line, total cost (₹ cr) | C35: 8
B36: Year of purchase | C36: FY27
B37: Machine life (years) | C37: 4
B38: Additional depreciation (FY27 onwards) | C38: =C35/C37
B39: Working capital (% of revenue) | C39: 0.2
B40: Working capital at 31 Mar 2026 (₹ cr) | C40: 29
B41: Tax rate | C41: 0.25
B42: Debt as on 31/3/2026 (₹ cr) | C42: 25
B43: Interest cost (%) | C43: 0.11
