Workbook

Sheet Financials>>

Sheet Offline retail
A1: Offline retail stores
A2: All figures in ₹ crore
A4: x | B4: Profit and loss
B5: Particulars | C5: FY24 | D5: FY25 | E5: FY26 | F5: FY27 | G5: FY28 | H5: FY29 | I5: FY30
B6: Bags revenue | C6: 8 | D6: 23 | E6: 53 | F6: =E6*(1+Assumptions!C6) -> 76.85 | G6: =F6*(1+Assumptions!D6) -> 103.7475 | H6: =G6*(1+Assumptions!E6) -> 132.7968 | I6: =H6*(1+Assumptions!F6) -> 162.0121
B7: Accessories revenue | C7: 2 | D7: 7 | E7: 17 | F7: =E7*(1+Assumptions!C7) -> 26.35 | G7: =F7*(1+Assumptions!D7) -> 38.2075 | H7: =G7*(1+Assumptions!E7) -> 51.580125 | I7: =H7*(1+Assumptions!F7) -> 66.02256
B8: Total revenue | C8: =C6+C7 -> 10 | D8: =D6+D7 -> 30 | E8: =E6+E7 -> 70 | F8: =F6+F7 -> 103.2 | G8: =G6+G7 -> 141.955 | H8: =H6+H7 -> 184.37693 | I8: =I6+I7 -> 228.03466
B9: Cost of goods sold | C9: 5.5 | D9: 15.6 | E9: 35 | F9: =F8*(1-Assumptions!C8) -> 51.6 | G9: =G8*(1-Assumptions!D8) -> 70.9775 | H9: =H8*(1-Assumptions!E8) -> 92.188463 | I9: =I8*(1-Assumptions!F8) -> 114.01733
B10: Gross margin | C10: =C8-C9 -> 4.5 | D10: =D8-D9 -> 14.4 | E10: =E8-E9 -> 35 | F10: =F8-F9 -> 51.6 | G10: =G8-G9 -> 70.9775 | H10: =H8-H9 -> 92.188463 | I10: =I8-I9 -> 114.01733
B11: Packaging | C11: 0.2 | D11: 0.4 | E11: 0.8 | F11: =F$8*Assumptions!C9 -> 1.2384 | G11: =G$8*Assumptions!D9 -> 1.41955 | H11: =H$8*Assumptions!E9 -> 2.2125231 | I11: =I$8*Assumptions!F9 -> 2.7364159
B12: Payment gateway charges | C12: 0.1 | D12: 0.3 | E12: 0.6 | F12: =F$8*Assumptions!C10 -> 0.8256 | G12: =G$8*Assumptions!D10 -> 1.13564 | H12: =H$8*Assumptions!E10 -> 1.4750154 | I12: =I$8*Assumptions!F10 -> 1.8242772
B13: Contribution Margin-1 | C13: =C10-C11-C12 -> 4.2 | D13: =D10-D11-D12 -> 13.7 | E13: =E10-E11-E12 -> 33.6 | F13: =F10-F11-F12 -> 49.536 | G13: =G10-G11-G12 -> 68.42231 | H13: =H10-H11-H12 -> 88.500924 | I13: =I10-I11-I12 -> 109.45663
B14: Performance Marketing | C14: 0.7 | D14: 1.8 | E14: 3.5 | F14: =F$8*Assumptions!C11 -> 5.16 | G14: =G$8*Assumptions!D11 -> 7.09775 | H14: =H$8*Assumptions!E11 -> 9.2188463 | I14: =I$8*Assumptions!F11 -> 11.401733
B15: Contribution Margin-2 | C15: =C13-C14 -> 3.5 | D15: =D13-D14 -> 11.9 | E15: =E13-E14 -> 30.1 | F15: =F13-F14 -> 44.376 | G15: =G13-G14 -> 61.32456 | H15: =H13-H14 -> 79.282078 | I15: =I13-I14 -> 98.054902
B16: Store rent | C16: 2.4 | D16: 5.4 | E16: 9.1 | F16: =E16*(1+Assumptions!C12) -> 12.012 | G16: =F16*(1+Assumptions!D12) -> 15.13512 | H16: =G16*(1+Assumptions!E12) -> 18.162144 | I16: =H16*(1+Assumptions!F12) -> 21.068087
B17: Store staff | C17: 1.8 | D17: 4.2 | E17: 7 | F17: =E17*(1+Assumptions!C13) -> 9.38 | G17: =F17*(1+Assumptions!D13) -> 12.0064 | H17: =G17*(1+Assumptions!E13) -> 14.647808 | I17: =H17*(1+Assumptions!F13) -> 17.284413
B18: Offline contribution | C18: =C15-C16-C17 -> -0.7 | D18: =D15-D16-D17 -> 2.3 | E18: =E15-E16-E17 -> 14 | F18: =F15-F16-F17 -> 22.984 | G18: =G15-G16-G17 -> 34.18304 | H18: =H15-H16-H17 -> 46.472126 | I18: =I15-I16-I17 -> 59.702402

Sheet D2C
A1: D2C & App
A2: All figures in ₹ crore
A4: x | B4: Profit and loss
B5: Particulars | C5: FY24 | D5: FY25 | E5: FY26 | F5: FY27 | G5: FY28 | H5: FY29 | I5: FY30
B6: Bags revenue | C6: 16 | D6: 35 | E6: 60 | F6: =E6*(1+Assumptions!C17) -> 84 | G6: =F6*(1+Assumptions!D17) -> 110.88 | H6: =G6*(1+Assumptions!E17) -> 138.6 | I6: =H6*(1+Assumptions!F17) -> 166.32
B7: Accessories revenue | C7: 4 | D7: 10 | E7: 20 | F7: =E7*(1+Assumptions!C18) -> 30 | G7: =F7*(1+Assumptions!D18) -> 42 | H7: =G7*(1+Assumptions!E18) -> 55.44 | I7: =H7*(1+Assumptions!F18) -> 69.3
B8: Total revenue | C8: =C6+C7 -> 20 | D8: =D6+D7 -> 45 | E8: =E6+E7 -> 80 | F8: =F6+F7 -> 114 | G8: =G6+G7 -> 152.88 | H8: =H6+H7 -> 194.04 | I8: =I6+I7 -> 235.62
B9: Cost of goods sold | C9: 10.2 | D9: 22.1 | E9: 37.6 | F9: =F8*(1-Assumptions!C19) -> 53.58 | G9: =G8*(1-Assumptions!D19) -> 71.8536 | H9: =H8*(1-Assumptions!E19) -> 91.1988 | I9: =I8*(1-Assumptions!F19) -> 110.7414
B10: Gross margin | C10: =C8-C9 -> 9.8 | D10: =D8-D9 -> 22.9 | E10: =E8-E9 -> 42.4 | F10: =F8-F9 -> 60.42 | G10: =G8-G9 -> 81.0264 | H10: =H8-H9 -> 102.8412 | I10: =I8-I9 -> 124.8786
B11: Packaging | C11: 0.3 | D11: 0.7 | E11: 1.2 | F11: =F$8*Assumptions!C20 -> 1.71 | G11: =G$8*Assumptions!D20 -> 2.2932 | H11: =H$8*Assumptions!E20 -> 2.9106 | I11: =I$8*Assumptions!F20 -> 3.5343
B12: Payment gateway charges | C12: 0.3 | D12: 0.7 | E12: 1.2 | F12: =F$8*Assumptions!C21 -> 1.71 | G12: =G$8*Assumptions!D21 -> 2.2932 | H12: =H$8*Assumptions!E21 -> 2.9106 | I12: =I$8*Assumptions!F21 -> 3.5343
B13: Shipping | C13: 0.6 | D13: 1.3 | E13: 2 | F13: =F$8*Assumptions!C22 -> 2.85 | G13: =G$8*Assumptions!D22 -> 3.822 | H13: =H$8*Assumptions!E22 -> 4.851 | I13: =I$8*Assumptions!F22 -> 5.8905
B14: Contribution Margin-1 | C14: =C10-C11-C12-C13 -> 8.6 | D14: =D10-D11-D12-D13 -> 20.2 | E14: =E10-E11-E12-E13 -> 38 | F14: =F10-F11-F12-F13 -> 54.15 | G14: =G10-G11-G12-G13 -> 72.618 | H14: =H10-H11-H12-H13 -> 92.169 | I14: =I10-I11-I12-I13 -> 111.9195
B15: Performance marketing | C15: 7.6 | D15: 14 | E15: 22 | F15: =F$8*Assumptions!C23 -> 29.64 | G15: =G$8*Assumptions!D23 -> 38.22 | H15: =H$8*Assumptions!E23 -> 46.5696 | I15: =I$8*Assumptions!F23 -> 54.1926
B16: D2C contribution | C16: =C14-C15 -> 1 | D16: =D14-D15 -> 6.2 | E16: =E14-E15 -> 16 | F16: =F14-F15 -> 24.51 | G16: =G14-G15 -> 34.398 | H16: =H14-H15 -> 45.5994 | I16: =I14-I15 -> 57.7269

Sheet Consolidated 
A1: Consolidated financials
A2: All figures in ₹ crore
A4: x | B4: Consolidated financials
B5: Particulars | C5: FY24 | D5: FY25 | E5: FY26 | F5: FY27 | G5: FY28 | H5: FY29 | I5: FY30
B6: Offline revenue | C6: ='Offline retail'!C8 -> 10 | D6: ='Offline retail'!D8 -> 30 | E6: ='Offline retail'!E8 -> 70 | F6: ='Offline retail'!F8 -> 103.2 | G6: ='Offline retail'!G8 -> 141.955 | H6: ='Offline retail'!H8 -> 184.37693 | I6: ='Offline retail'!I8 -> 228.03466
B7: D2C revenue | C7: =D2C!C8 -> 20 | D7: =D2C!D8 -> 45 | E7: =D2C!E8 -> 80 | F7: =D2C!F8 -> 114 | G7: =D2C!G8 -> 152.88 | H7: =D2C!H8 -> 194.04 | I7: =D2C!I8 -> 235.62
B8: Total revenue | C8: =C6+C7 -> 30 | D8: =D6+D7 -> 75 | E8: =E6+E7 -> 150 | F8: =F6+F7 -> 217.2 | G8: =G6+G7 -> 294.835 | H8: =H6+H7 -> 378.41693 | I8: =I6+I7 -> 463.65466
B9: Offline contribution | C9: ='Offline retail'!C18 -> -0.7 | D9: ='Offline retail'!D18 -> 2.3 | E9: ='Offline retail'!E18 -> 14 | F9: ='Offline retail'!F18 -> 22.984 | G9: ='Offline retail'!G18 -> 34.18304 | H9: ='Offline retail'!H18 -> 46.472126 | I9: ='Offline retail'!I18 -> 59.702402
B10: D2C contribution | C10: =D2C!C16 -> 1 | D10: =D2C!D16 -> 6.2 | E10: =D2C!E16 -> 16 | F10: =D2C!F16 -> 24.51 | G10: =D2C!G16 -> 34.398 | H10: =D2C!H16 -> 45.5994 | I10: =D2C!I16 -> 57.7269
B11: Total contribution | C11: =C9+C10 -> 0.3 | D11: =D9+D10 -> 8.5 | E11: =E9+E10 -> 30 | F11: =F9+F10 -> 47.494 | G11: =G9+G10 -> 68.58104 | H11: =H9+H10 -> 92.071526 | I11: =I9+I10 -> 117.4293
B12: Head office salaries | C12: 2.6 | D12: 4 | E12: 6 | F12: =E12*(1+Assumptions!C27) -> 7.8 | G12: =F12*(1+Assumptions!D27) -> 9.75 | H12: =G12*(1+Assumptions!E27) -> 11.7 | I12: =H12*(1+Assumptions!F27) -> 13.572
B13: Brand marketing | C13: 1.4 | D13: 2.2 | E13: 3.4 | F13: =E13*(1+Assumptions!C28) -> 4.76 | G13: =F13*(1+Assumptions!D28) -> 6.426 | H13: =G13*(1+Assumptions!E28) -> 8.3538 | I13: =H13*(1+Assumptions!F28) -> 10.44225
B14: Technology and platform | C14: 0.5 | D14: 0.9 | E14: 1.5 | F14: =E14*(1+Assumptions!C29) -> 1.95 | G14: =F14*(1+Assumptions!D29) -> 2.4375 | H14: =G14*(1+Assumptions!E29) -> 2.925 | I14: =H14*(1+Assumptions!F29) -> 3.36375
B15: Other general and administrative | C15: 0.5 | D15: 0.9 | E15: 1.5 | F15: =E15*(1+Assumptions!C30) -> 1.875 | G15: =F15*(1+Assumptions!D30) -> 2.2875 | H15: =G15*(1+Assumptions!E30) -> 2.69925 | I15: =H15*(1+Assumptions!F30) -> 3.1041375
B16: EBITDA | C16: =C11-C12-C13-C14-C15 -> -4.7 | D16: =D11-D12-D13-D14-D15 -> 0.5 | E16: =E11-E12-E13-E14-E15 -> 17.6 | F16: =F11-SUM(F12:F15) -> 31.109 | G16: =G11-SUM(G12:G15) -> 47.68004 | H16: =H11-SUM(H12:H15) -> 66.393476 | I16: =I11-SUM(I12:I15) -> 86.947164
B17: Depreciation | C17: 0.5 | D17: 1.5 | E17: 3 | F17: =Assumptions!$C$34 -> 3 | G17: =Assumptions!$C$34+Assumptions!$C$38 -> 4.2 | H17: =Assumptions!$C$34+Assumptions!$C$38 -> 4.2 | I17: =Assumptions!$C$34+Assumptions!$C$38 -> 4.2
B18: EBIT | C18: =C16-C17 -> -5.2 | D18: =D16-D17 -> -1 | E18: =E16-E17 -> 14.6 | F18: =F16-F17 -> 28.109 | G18: =G16-G17 -> 43.48004 | H18: =H16-H17 -> 62.193476 | I18: =I16-I17 -> 82.747164
B19: Interest | C19: 0 | D19: 0 | E19: 0 | F19: =Assumptions!$C$42*Assumptions!$C$43 -> 4 | G19: =Assumptions!$C$42*Assumptions!$C$43 -> 4 | H19: =Assumptions!$C$42*Assumptions!$C$43 -> 4 | I19: =Assumptions!$C$42*Assumptions!$C$43 -> 4
B20: Profit before tax | C20: =C18-C19 -> -5.2 | D20: =D18-D19 -> -1 | E20: =E18-E19 -> 14.6 | F20: =F18-F19 -> 24.109 | G20: =G18-G19 -> 39.48004 | H20: =H18-H19 -> 58.193476 | I20: =I18-I19 -> 78.747164
B21: Tax | C21: =MAX(0,C20*Assumptions!$C$41) -> 0 | D21: =MAX(0,D20*Assumptions!$C$41) -> 0 | E21: =MAX(0,E20*Assumptions!$C$41) -> 3.65 | F21: =MAX(0,F20*Assumptions!$C$41) -> 6.02725 | G21: =G20*Assumptions!$C$41 -> 9.87001 | H21: =H20*Assumptions!$C$41 -> 14.548369 | I21: =I20*Assumptions!$C$41 -> 19.686791
B22: Profit after tax | C22: =C20-C21 -> -5.2 | D22: =D20-D21 -> -1 | E22: =E20-E21 -> 10.95 | F22: =F20-F21 -> 18.08175 | G22: =G20-G21 -> 29.61003 | H22: =H20-H21 -> 43.645107 | I22: =I20-I21 -> 59.060373

Sheet Valuation>>

Sheet DCF (FCFE)
A1: Discounted Cash Flow Valuation (FCFE)
A2: All figures in ₹ crore
A4: x | B4: Discounting factor
A5: x | B5: Terminal growth rate
A7: x | B7: Calculating value of Cool Nomad using DCF
B8: Particulars | C8: FY27 | D8: FY28 | E8: FY29 | F8: FY30
B9: Profit after tax
B10: Add: non-cash expenses
B11: Cash profit (for equity holders)
B12: Less: Additional working capital required
B13: Less: Capex for engraving machines
B14: Free cash flows for equity (FCFE)
B15: Terminal value
A17: x | B17: Years to discount
B18: Discounting factor
A20: x | B20: Present value of free cash flows
B21: Present value of terminal value
A23: x | B23: Equity value as per DCF
A25: x | B25: Calculating Net Present Value (NPV)
B26: Particulars | C26: 46112
B27: Investor's preferred value
B28: Founder's preferred value
B29: Net present Value (NPV)
A31: x | B31: Calculating Internal Rate of Return (IRR)
B32: Particulars | C32: 46112 | D32: 46477 | E32: 46843 | F32: 47208 | G32: 47573
B33: Cash flows
B34: Internal Rate of Return (IRR)
A36: x | B36: Scenarios
B37: Case | C37: Multiple of base | D37: Valuation
B38: Upside
B39: Base
B40: Downside
A42: x | B42: Working for working capital
B43: Particulars | C43: FY26 | D43: FY27 | E43: FY28 | F43: FY29 | G43: FY30
B44: Working capital
B45: Increase

Sheet Relative Valuation
A1: Relative Valuation

Sheet Sum of parts
A1: Sum of parts valuation

Sheet First Chicago
A1: First Chicago Method

Sheet Exit Pegged Valuation
A1: First Chicago Method

Sheet Football Field
A1: Football field

Sheet Assumptions
A1: Assumptions Sheet
A4: x | B4: Offline retail
B5: Particulars | C5: FY27 | D5: FY28 | E5: FY29 | F5: FY30
B6: Bags revenue growth (YoY) | C6: 0.45 | D6: 0.35 | E6: 0.28 | F6: 0.22
B7: Accessories revenue growth (YoY) | C7: 0.55 | D7: 0.45 | E7: 0.35 | F7: 0.28
B8: Gross margin (% of revenue) | C8: 0.5 | D8: 0.5 | E8: 0.5 | F8: 0.5
B9: Packaging (% of revenue) | C9: 0.012 | D9: 0.01 | E9: 0.012 | F9: 0.012
B10: Payment gateway (% of revenue) | C10: 0.008 | D10: 0.008 | E10: 0.008 | F10: 0.008
B11: Performance marketing (% of revenue) | C11: 0.05 | D11: 0.05 | E11: 0.05 | F11: 0.05
B12: Store rent (YoY) | C12: 0.32 | D12: 0.26 | E12: 0.2 | F12: 0.16
B13: Store staff (YoY) | C13: 0.34 | D13: 0.28 | E13: 0.22 | F13: 0.18
A15: x | B15: D2C
B16: Particulars | C16: FY27 | D16: FY28 | E16: FY29 | F16: FY30
B17: Bags revenue growth (YoY) | C17: 0.4 | D17: 0.32 | E17: 0.25 | F17: 0.2
B18: Accessories revenue growth (YoY) | C18: 0.5 | D18: 0.4 | E18: 0.32 | F18: 0.25
B19: Gross margin (% of revenue) | C19: 0.53 | D19: 0.53 | E19: 0.53 | F19: 0.53
B20: Packaging (% of revenue) | C20: 0.015 | D20: 0.015 | E20: 0.015 | F20: 0.015
B21: Payment gateway (% of revenue) | C21: 0.015 | D21: 0.015 | E21: 0.015 | F21: 0.015
B22: Shipping (% of revenue) | C22: 0.025 | D22: 0.025 | E22: 0.025 | F22: 0.025
B23: Performance marketing (% of revenue) | C23: 0.26 | D23: 0.25 | E23: 0.24 | F23: 0.23
A25: x | B25: Common cost growth (YoY)
B26: Particulars | C26: FY27 | D26: FY28 | E26: FY29 | F26: FY30
B27: Head office salaries | C27: 0.3 | D27: 0.25 | E27: 0.2 | F27: 0.16
B28: Brand marketing | C28: 0.4 | D28: 0.35 | E28: 0.3 | F28: 0.25
B29: Technology and platform | C29: 0.3 | D29: 0.25 | E29: 0.2 | F29: 0.15
B30: Other general and administrative | C30: 0.25 | D30: 0.22 | E30: 0.18 | F30: 0.15
A32: x | B32: Corporate
B33: Particulars | C33: Value
B34: Depreciation on existing fit-outs p.a. (₹ cr) (FY26 onwards) | C34: 3
B35: Engraving machines, total cost (₹ cr) | C35: 6
B36: Year of purchase | C36: FY28
B37: Machine life (years) | C37: 5
B38: Additional depreciation (FY28 onwards) | C38: =C35/C37 -> 1.2
B39: Working capital (% of revenue) | C39: 0.18
B40: Working capital at 31 Mar 2026 (₹ cr) | C40: 27
B41: Tax rate | C41: 0.25
B42: Debt as on 31/3/2026 (₹ cr) | C42: 40
B43: Interest cost (%) | C43: 0.1
B44: Equity as on 31/3/2026 (₹ cr) | C44: 26
